mesa_designer/__init__.py
mesa_designer/mesa.py
mesa_designer/part.py
mesa_designer/py.typed
mesa_designer/data/FRET/ICDs.json
mesa_designer/data/aip/aip_list.json
mesa_designer/data/intracellular/CTEV_list.json
mesa_designer/data/intracellular/NTEV_list.json
mesa_designer/data/intracellular/TEVp_list.json
mesa_designer/data/prs/prs_list.json
mesa_designer/data/signal_seqs/signal_sequences.json
mesa_designer/data/signal_seqs/unknown_signal_sequence.json
mesa_designer/data/tags/tag_sequences.json
mesa_designer/data/tmd/tmd_list.json
mesa_designer/img/dark.png
mesa_designer-1.0.0.dist-info/METADATA
mesa_designer-1.0.0.dist-info/WHEEL
mesa_designer-1.0.0.dist-info/licenses/LICENSE
mesa_designer-1.0.0.dist-info/RECORD
