Metadata-Version: 2.4
Name: mesa-designer
Version: 1.0.0
Summary: MESA-Designer python package
Project-URL: Homepage, https://github.com/igem-munich/mesa-designer-package
Project-URL: Issues, https://github.com/igem-munich/mesa-designer-package/issues
Author-email: Aeneas Tews <aeneas.tews@icloud.com>
License-Expression: CC-BY-4.0
License-File: LICENSE
Classifier: Operating System :: OS Independent
Classifier: Programming Language :: Python :: 3
Requires-Python: >=3.12
Requires-Dist: biopython>=1.85
